LICENSE.txt
MANIFEST.in
README.md
requirements.txt
setup.py
tox.ini
ioisis/__init__.py
ioisis/__main__.py
ioisis/bruma.py
ioisis/ccons.py
ioisis/fieldutils.py
ioisis/iso.py
ioisis/java.py
ioisis/mst.py
ioisis/streamutils.py
ioisis.egg-info/PKG-INFO
ioisis.egg-info/SOURCES.txt
ioisis.egg-info/dependency_links.txt
ioisis.egg-info/entry_points.txt
ioisis.egg-info/requires.txt
ioisis.egg-info/top_level.txt
tests/__init__.py
tests/test_cli.py
tests/test_fieldutils.py
tests/test_iso.py
tests/test_java.py