Metadata-Version: 2.1
Name: ioisis
Version: 0.3.0
Summary: I/O for ISIS files in Python
Home-page: https://github.com/scieloorg/ioisis
Author: Danilo de Jesus da Silva Bellini
Author-email: danilo.bellini@gmail.com
License: 2-clause BSD
Platform: UNKNOWN
Classifier: Development Status :: 2 - Pre-Alpha
Classifier: Environment :: Console
Classifier: Environment :: Other Environment
Classifier: Intended Audience :: Science/Research
Classifier: License :: OSI Approved :: BSD License
Classifier: Programming Language :: Java
Classifier: Programming Language :: Python :: 3
Classifier: Programming Language :: Python :: 3.6
Classifier: Programming Language :: Python :: 3.7
Classifier: Programming Language :: Python :: 3.8
Classifier: Programming Language :: Python :: 3 :: Only
Classifier: Topic :: Database
Classifier: Topic :: Scientific/Engineering :: Information Analysis
Classifier: Operating System :: OS Independent
Requires-Python: >=3.6
